langcrew/__init__.py
langcrew/agent.py
langcrew/crew.py
langcrew/guardrail.py
langcrew/llm_factory.py
langcrew/project.py
langcrew/prompt_builder.py
langcrew/runnable_crew.py
langcrew/task.py
langcrew/types.py
langcrew/context/__init__.py
langcrew/context/config.py
langcrew/context/hooks.py
langcrew/context/processor.py
langcrew/context/token_utils.py
langcrew/context/tool_call_compressor.py
langcrew/executors/__init__.py
langcrew/executors/base.py
langcrew/executors/factory.py
langcrew/executors/react_executor.py
langcrew/hitl/__init__.py
langcrew/hitl/config.py
langcrew/hitl/tool_wrapper.py
langcrew/llm/__init__.py
langcrew/llm/bedrock_decorator.py
langcrew/llm/vertex_chat_model.py
langcrew/memory/__init__.py
langcrew/memory/config.py
langcrew/memory/context.py
langcrew/memory/factory.py
langcrew/tools/__init__.py
langcrew/tools/astream_tool.py
langcrew/tools/converter.py
langcrew/tools/mcp.py
langcrew/tools/registry.py
langcrew/utils/__init__.py
langcrew/utils/async_utils.py
langcrew/utils/checkpointer_utils.py
langcrew/utils/file_detect.py
langcrew/utils/language.py
langcrew/utils/message_utils.py
langcrew/utils/runnable_config_utils.py
langcrew/web/__init__.py
langcrew/web/adapter.py
langcrew/web/factory.py
langcrew/web/http_server.py
langcrew/web/protocol.py
langcrew/web/tool_display.py
langcrew-0.1.1.dist-info/METADATA
langcrew-0.1.1.dist-info/WHEEL
langcrew-0.1.1.dist-info/licenses/LICENSE
langcrew-0.1.1.dist-info/RECORD
