Metadata-Version: 2.4
Name: langcrew
Version: 0.1.1
Summary: A LangChain-based crew management system
Project-URL: Homepage, https://langcrew.ai/
Project-URL: Repository, https://github.com/01-ai/langcrew
Project-URL: Documentation, https://langcrew.ai/guides/quickstart/
Project-URL: Issues, https://github.com/01-ai/langcrew/issues
Author-email: BTM Team <btm@langcrew.ai>
License-File: LICENSE
Keywords: agents,ai,langchain,llm,multi-agent,orchestration
Classifier: Development Status :: 3 - Alpha
Classifier: Intended Audience :: Developers
Classifier: License :: OSI Approved :: MIT License
Classifier: Programming Language :: Python :: 3
Classifier: Programming Language :: Python :: 3.10
Classifier: Programming Language :: Python :: 3.11
Classifier: Programming Language :: Python :: 3.12
Requires-Python: >=3.10
Requires-Dist: aiobotocore>=2.23.1
Requires-Dist: boto3<2.0.0,>=1.39.6
Requires-Dist: crewai<0.150.0
Requires-Dist: fastapi>=0.104.0
Requires-Dist: google-genai>=1.39.0
Requires-Dist: httpx>=0.25.0
Requires-Dist: langchain-anthropic>=0.1.0
Requires-Dist: langchain-aws>=0.2.28
Requires-Dist: langchain-community>=0.3.24
Requires-Dist: langchain-core>=0.3.72
Requires-Dist: langchain-mcp-adapters>=0.1.7
Requires-Dist: langchain-openai>=0.2.1
Requires-Dist: langchain>=0.1.0
Requires-Dist: langgraph-checkpoint-sqlite>=2.0.10
Requires-Dist: langgraph-supervisor>=0.0.27
Requires-Dist: langgraph>=0.6.0
Requires-Dist: langmem
Requires-Dist: mcp>=0.1.0
Requires-Dist: pydantic>=2.0.0
Requires-Dist: python-dotenv>=1.0.0
Requires-Dist: uvicorn>=0.24.0
Provides-Extra: all-backends
Requires-Dist: langgraph-checkpoint-mongodb>=0.1.4; extra == 'all-backends'
Requires-Dist: langgraph-checkpoint-mysql[aiomysql,asyncmy,pymysql]>=2.0.17; extra == 'all-backends'
Requires-Dist: langgraph-checkpoint-postgres>=2.0.23; extra == 'all-backends'
Requires-Dist: langgraph-checkpoint-redis>=0.0.8; extra == 'all-backends'
Requires-Dist: langgraph-store-mongodb>=0.0.1; extra == 'all-backends'
Provides-Extra: mongodb
Requires-Dist: langgraph-checkpoint-mongodb>=0.1.4; extra == 'mongodb'
Requires-Dist: langgraph-store-mongodb>=0.0.1; extra == 'mongodb'
Provides-Extra: mysql
Requires-Dist: langgraph-checkpoint-mysql[aiomysql,pymysql]>=2.0.17; extra == 'mysql'
Provides-Extra: postgres
Requires-Dist: langgraph-checkpoint-postgres>=2.0.23; extra == 'postgres'
Provides-Extra: redis
Requires-Dist: langgraph-checkpoint-redis>=0.0.8; extra == 'redis'
